cloudio_connector.py
cloudio_connector_python-1.2.3.dist-info/LICENSE
cloudio_connector_python-1.2.3.dist-info/METADATA
cloudio_connector_python-1.2.3.dist-info/WHEEL
cloudio_connector_python-1.2.3.dist-info/top_level.txt
cloudio_connector_python-1.2.3.dist-info/RECORD
