Metadata-Version: 2.1
Name: cloudio-connector-python
Version: 1.2.3
Summary: Helper to create python cloudio applications
Author-email: Martin Meyer <meyer.mart@outlook.com>
License: MIT License
Project-URL: Homepage, http://cloudio.hevs.ch/
Project-URL: Repository, https://github.com/cloudio-project/cloudio-connector-python
Keywords: cloudio,cloud.io,application,connector
Requires-Python: >=3.9
License-File: LICENSE
Requires-Dist: pandas
Requires-Dist: requests
Requires-Dist: cbor
Requires-Dist: paho-mqtt
